django_rangepaginator/__init__.py
django_rangepaginator/layout.py
django_rangepaginator/templates/django_rangepaginator/bootstrap3.html
django_rangepaginator/templates/django_rangepaginator/bootstrap4.html
django_rangepaginator/templates/django_rangepaginator/link_tags.html
django_rangepaginator/templatetags/__init__.py
django_rangepaginator/templatetags/rangepaginator.py
django_rangepaginator-1.2.0.dist-info/DESCRIPTION.rst
django_rangepaginator-1.2.0.dist-info/METADATA
django_rangepaginator-1.2.0.dist-info/RECORD
django_rangepaginator-1.2.0.dist-info/WHEEL
django_rangepaginator-1.2.0.dist-info/metadata.json
django_rangepaginator-1.2.0.dist-info/top_level.txt
