Metadata-Version: 2.0
Name: django-rangepaginator
Version: 1.2.0
Summary: Nice paginator for Django
Home-page: https://github.com/mvantellingen/django-rangepaginator
Author: Michael van Tellingen
Author-email: michaelvantellingen@gmail.com
License: MIT
Platform: UNKNOWN
Classifier: Development Status :: 5 - Production/Stable
Classifier: Environment :: Web Environment
Classifier: Framework :: Django
Classifier: Framework :: Django :: 1.8
Classifier: Framework :: Django :: 1.9
Classifier: Framework :: Django :: 1.10
Classifier: Framework :: Django :: 1.11
Classifier: Framework :: Django :: 2.0
Classifier: License :: OSI Approved :: MIT License
Classifier: Programming Language :: Python
Classifier: Programming Language :: Python :: 2
Classifier: Programming Language :: Python :: 2.7
Classifier: Programming Language :: Python :: 3
Classifier: Programming Language :: Python :: 3.4
Classifier: Programming Language :: Python :: 3.5
Classifier: Programming Language :: Python :: 3.6
Provides-Extra: docs
Provides-Extra: test
Requires-Dist: Django (>=1.7)
Requires-Dist: furl (>=1.0)
Requires-Dist: six (>=1.1)
Provides-Extra: docs
Requires-Dist: sphinx (>=1.4.0); extra == 'docs'
Provides-Extra: test
Requires-Dist: pytest (==3.0.1); extra == 'test'
Requires-Dist: pytest-cov (==2.3.1); extra == 'test'
Requires-Dist: pytest-django (==3.0.0); extra == 'test'
Requires-Dist: pytest-sugar (==0.7.1); extra == 'test'
Requires-Dist: isort (==4.2.5); extra == 'test'
Requires-Dist: flake8 (==3.0.4); extra == 'test'
Requires-Dist: flake8-blind-except (==0.1.1); extra == 'test'
Requires-Dist: flake8-debugger (==1.4.0); extra == 'test'
